[
  {
    "id": "msg_6f4fbaf2-bbb2-45c8-a23b-a132dbae8476",
    "name": "Tyay",
    "email": "Taya@gmail.com",
    "message": "Taya",
    "timestamp": "2025-08-29T09:46:51.227Z"
  },
  {
    "id": "msg_66e72070-b9b3-443f-aab9-69bbe15df03a",
    "name": "Rudraksh",
    "email": "rudraksh@gmail.com",
    "message": "Hello",
    "timestamp": "2025-09-03T13:35:52.931Z"
  },
  {
    "id": "msg_7ca5a684-41b2-4cdd-af61-2457f8958b6c",
    "name": "Hello",
    "email": "Hello@gmail.com",
    "message": "Hello",
    "timestamp": "2025-09-03T13:37:58.024Z"
  },
  {
    "id": "msg_36fe7d63-97f1-4482-903a-31e32ade421e",
    "name": "Hello",
    "email": "taya@gmail.com",
    "message": "Hello",
    "timestamp": "2025-09-03T13:39:32.343Z"
  }
]